pinhop/__init__.py
pinhop/css.py
pinhop/pinhop.py
pinhop-0.3.0.dist-info/METADATA
pinhop-0.3.0.dist-info/WHEEL
pinhop-0.3.0.dist-info/entry_points.txt
pinhop-0.3.0.dist-info/top_level.txt
pinhop-0.3.0.dist-info/RECORD
