Metadata-Version: 2.1
Name: pinhop
Version: 0.3.0
Summary: Timehop for Pinboard
Home-page: https://github.com/mikepqr/pinhop
Author: Mike Lee Williams
Author-email: mike@mike.place
Project-URL: Bug Reports, https://github.com/mikepqr/pinhop/issues
Project-URL: Source, https://github.com/mikepqr/pinhop
Keywords: twitter
Classifier: Development Status :: 4 - Beta
Classifier: Environment :: Console
Classifier: Intended Audience :: End Users/Desktop
Classifier: Topic :: Utilities
Classifier: License :: OSI Approved :: MIT License
Classifier: Programming Language :: Python :: 3
Classifier: Programming Language :: Python :: 3.9
Classifier: Programming Language :: Python :: 3.10
Classifier: Programming Language :: Python :: 3.11
Classifier: Programming Language :: Python :: 3 :: Only
Requires-Python: >=3.9
Requires-Dist: tqdm
Requires-Dist: typer
